candl/__init__.py
candl/nn.py
candl/tensor.py
candl-0.0.7.dist-info/LICENSE
candl-0.0.7.dist-info/METADATA
candl-0.0.7.dist-info/WHEEL
candl-0.0.7.dist-info/top_level.txt
candl-0.0.7.dist-info/RECORD
