Metadata-Version: 2.1
Name: candl
Version: 0.0.7
Summary: A tiny, pedagogical neural network library with a pytorch-like API.
Home-page: https://github.com/sripkunda/candl/
Author: Sri Pranav Kunda
Author-email: sripkunda@gmail.com
License: UNKNOWN
Project-URL: Bug Tracker, https://github.com/sripkunda/candl/issues
Platform: UNKNOWN
Classifier: Programming Language :: Python :: 3
Classifier: License :: OSI Approved :: MIT License
Classifier: Operating System :: OS Independent
Requires-Python: >=3.6
